pytsv/__init__.py
pytsv/configs.py
pytsv/core.py
pytsv/main.py
pytsv/static.py
pytsv-0.1.75.dist-info/METADATA
pytsv-0.1.75.dist-info/WHEEL
pytsv-0.1.75.dist-info/entry_points.txt
pytsv-0.1.75.dist-info/licenses/LICENSE
pytsv-0.1.75.dist-info/RECORD
