Metadata-Version: 2.4
Name: pytsv
Version: 0.1.75
Summary: Pytsv is a the Swiss army knife for TSV files
Project-URL: Homepage, https://github.com/veltzer/pytsv
Project-URL: Bug Tracker, https://github.com/veltzer/pytsv/issues
Project-URL: Documentation, https://veltzer.github.io/pytsv
Project-URL: Download, https://pypi.org/project/pytsv/
Project-URL: Repository, https://github.com/veltzer/pytsv
Author-email: Mark Veltzer <mark.veltzer@gmail.com>
Maintainer-email: Mark Veltzer <mark.veltzer@gmail.com>
License-Expression: MIT
License-File: LICENSE
Keywords: csv,format,python,tsv
Classifier: Development Status :: 4 - Beta
Classifier: Environment :: Console
Classifier: License :: OSI Approved :: MIT License
Classifier: Operating System :: OS Independent
Classifier: Programming Language :: Python
Classifier: Programming Language :: Python :: 3
Classifier: Programming Language :: Python :: 3 :: Only
Classifier: Programming Language :: Python :: 3.12
Classifier: Topic :: Utilities
Requires-Python: >=3.12
Requires-Dist: attrs
Requires-Dist: numpy
Requires-Dist: pandas
Requires-Dist: pyanyzip
Requires-Dist: pylogconf
Requires-Dist: pytconf
Requires-Dist: tqdm
